README.rst
setup.py
notify_push.egg-info/PKG-INFO
notify_push.egg-info/SOURCES.txt
notify_push.egg-info/dependency_links.txt
notify_push.egg-info/entry_points.txt
notify_push.egg-info/top_level.txt
notifypush/__init__.py
notifypush/__main__.py
notifypush/services/__init__.py
notifypush/services/notifcasterbot.py
notifypush/services/pushitbot.py