Metadata-Version: 1.1
Name: notify-push
Version: 0.0.3
Summary: Push notifications straight to your phone using multiple services
Home-page: https://github.com/fopina/notify-push
Author: Filipe Pina
Author-email: fopina@skmobi.com
License: MIT
Download-URL: https://github.com/fopina/notify-push/tarball/v0.0.3
Keywords: push,notifications,alerts,messages
Platform: UNKNOWN
Classifier: Development Status :: 4 - Beta
Classifier: Intended Audience :: Developers
Classifier: License :: OSI Approved :: MIT License
Classifier: Operating System :: OS Independent
Classifier: Programming Language :: Python
Classifier: Programming Language :: Python
Classifier: Programming Language :: Python :: 2
Classifier: Programming Language :: Python :: 2.7
Classifier: Programming Language :: Python :: 3
Classifier: Programming Language :: Python :: 3.0
Classifier: Programming Language :: Python :: 3.1
Classifier: Programming Language :: Python :: 3.2
Classifier: Programming Language :: Python :: 3.3
Classifier: Programming Language :: Python :: 3.4
Classifier: Programming Language :: Python :: 3.5
